rs_fusion_datasets/__init__.py
rs_fusion_datasets/core/_fetch_augsburg.py
rs_fusion_datasets/core/_fetch_houston2013_mat.py
rs_fusion_datasets/core/_fetch_houston2018.py
rs_fusion_datasets/core/_fetch_muufl_mat.py
rs_fusion_datasets/core/_fetch_trento_mat.py
rs_fusion_datasets/core/common.py
rs_fusion_datasets/core/fetch_augsburg_ouc.py
rs_fusion_datasets/core/fetch_berlin_ouc.py
rs_fusion_datasets/core/fetch_houston2013.py
rs_fusion_datasets/core/fetch_houston2013_mmr.py
rs_fusion_datasets/core/fetch_houston2018_ouc.py
rs_fusion_datasets/core/fetch_muufl.py
rs_fusion_datasets/core/fetch_trento.py
rs_fusion_datasets/torch/common_hsi_dsm_dataset.py
rs_fusion_datasets/torch/datasets.py
rs_fusion_datasets/util/benchmarker.py
rs_fusion_datasets/util/fileio.py
rs_fusion_datasets/util/hsi2rgb.py
rs_fusion_datasets/util/lbl2rgb.py
rs_fusion_datasets/util/patchify.py
rs_fusion_datasets/util/split_spmatrix.py
rs_fusion_datasets/util/transforms.py
rs_fusion_datasets-0.17.1.dist-info/METADATA
rs_fusion_datasets-0.17.1.dist-info/WHEEL
rs_fusion_datasets-0.17.1.dist-info/licenses/LICENSE
rs_fusion_datasets-0.17.1.dist-info/RECORD
