Metadata-Version: 2.4
Name: rs-fusion-datasets
Version: 0.17.1
Summary: Remote Sensing Data-Fetcher and Data-Loader for Joint Classification of Hyperspectral and LiDAR Data
Project-URL: Documentation, https://github.com/songyz2019/rs-fusion-datasets#readme
Project-URL: Issues, https://github.com/songyz2019/rs-fusion-datasets/issues
Project-URL: Source, https://github.com/songyz2019/rs-fusion-datasets
Author-email: songyz2019 <songyz2023dlut@outlook.com>
License-Expression: Apache-2.0
License-File: LICENSE
Classifier: Development Status :: 4 - Beta
Classifier: Programming Language :: Python
Classifier: Programming Language :: Python :: 3.9
Classifier: Programming Language :: Python :: 3.10
Classifier: Programming Language :: Python :: 3.11
Classifier: Programming Language :: Python :: 3.12
Classifier: Programming Language :: Python :: 3.13
Classifier: Programming Language :: Python :: Implementation :: CPython
Classifier: Programming Language :: Python :: Implementation :: PyPy
Requires-Python: >=3.9
Requires-Dist: jaxtyping>=0.2.0
Requires-Dist: numpy>=1.24.0
Requires-Dist: rasterio>=1.2.0
Requires-Dist: scikit-image>=0.21.0
Requires-Dist: scipy>=1.10.0
